pushikoo_getter_skland/__init__.py
pushikoo_getter_skland/config.py
pushikoo_getter_skland/main.py
pushikoo_getter_skland-0.1.0.dist-info/licenses/LICENSE
pushikoo_getter_skland-0.1.0.dist-info/METADATA
pushikoo_getter_skland-0.1.0.dist-info/WHEEL
pushikoo_getter_skland-0.1.0.dist-info/entry_points.txt
pushikoo_getter_skland-0.1.0.dist-info/top_level.txt
pushikoo_getter_skland-0.1.0.dist-info/RECORD
