Metadata-Version: 2.4
Name: pushikoo-getter-skland
Version: 0.1.0
Summary: Skland (森空岛) getter for Pushikoo
Author: Pushikoo
Project-URL: Homepage, https://github.com/EvATive7Cloud/pushikoo-getter-skland
Classifier: Programming Language :: Python :: 3
Classifier: Operating System :: OS Independent
Requires-Python: >=3.10
License-File: LICENSE
Requires-Dist: pushikoo-interface>=0.3.1
Requires-Dist: requests
Requires-Dist: loguru
Requires-Dist: hypergryph-api
Requires-Dist: skland-api
Provides-Extra: dev
Requires-Dist: ruff; extra == "dev"
Requires-Dist: pytest; extra == "dev"
Requires-Dist: python-dotenv; extra == "dev"
Dynamic: license-file
